happyset/DirFile.py
happyset/__init__.py
happyset/calc.py
happyset/getData.py
happyset/other.py
happyset/tokeniz.py
happyset/writeData.py
happyset-2.0.0.dist-info/WHEEL
happyset-2.0.0.dist-info/METADATA
happyset-2.0.0.dist-info/RECORD
