Metadata-Version: 2.4
Name: happyset
Version: 2.0.0
Summary: Frequently used processes are made into functions
Author: Nao Yamanouchi
Requires-Python: >=3.10.5
Requires-Dist: sudachipy >=0.6
Requires-Dist: sudachidict_core >=20250825
Requires-Dist: sudachidict_full >=20250825
Requires-Dist: mecab >=0.996
Requires-Dist: unidic >=1.1
Requires-Dist: opencv-python >=4.12
Requires-Dist: qrcode >=8.0
Requires-Dist: scipy >=1.16
Project-URL: Issues, https://github.com/ClairdelunaEve/pyfunc_happyset/issues
Project-URL: Source, https://github.com/ClairdelunaEve/pyfunc_happyset.git
